mortal_pipu/__init__.py
mortal_pipu/cli.pyd
mortal_pipu/cli.so
mortal_pipu-0.0.4.dist-info/METADATA
mortal_pipu-0.0.4.dist-info/WHEEL
mortal_pipu-0.0.4.dist-info/entry_points.txt
mortal_pipu-0.0.4.dist-info/top_level.txt
mortal_pipu-0.0.4.dist-info/RECORD
